bayesian_g_estimator/__init__.py
bayesian_g_estimator/core.py
bayesian_g_estimator-0.1.0.dist-info/licenses/LICENSE
bayesian_g_estimator-0.1.0.dist-info/METADATA
bayesian_g_estimator-0.1.0.dist-info/WHEEL
bayesian_g_estimator-0.1.0.dist-info/top_level.txt
bayesian_g_estimator-0.1.0.dist-info/RECORD
