Metadata-Version: 2.4
Name: bayesian_g_estimator
Version: 0.1.0
Summary: Estimate latent traits with Bayesian methods.
Author-email: Joseph Bronski <josephbronski7@protonmail.com>
License: MIT License
Project-URL: Homepage, https://github.com/yourusername/bayesian_g_estimator
Requires-Python: >=3.7
License-File: LICENSE
Requires-Dist: matplotlib>=3.0
Requires-Dist: numpy>=1.18
Requires-Dist: scipy>=1.4
Dynamic: license-file
